notify_stats/__init__.py
notify_stats-0.0.1.dist-info/LICENSE
notify_stats-0.0.1.dist-info/METADATA
notify_stats-0.0.1.dist-info/WHEEL
notify_stats-0.0.1.dist-info/top_level.txt
notify_stats-0.0.1.dist-info/RECORD
